ChiMera/__init__.py
ChiMera/chimera_core.py
ChiMera/dependencies/__init__.py
ChiMera/dependencies/all_metabo_paths/__init__.py
ChiMera/tools/__init__.py
ChiMera/tools/path_harvest.py
ChiMera/tools/silencer.py
ChiMera_ModelBuilder-2.0.15.dist-info/LICENSE
ChiMera_ModelBuilder-2.0.15.dist-info/METADATA
ChiMera_ModelBuilder-2.0.15.dist-info/WHEEL
ChiMera_ModelBuilder-2.0.15.dist-info/entry_points.txt
ChiMera_ModelBuilder-2.0.15.dist-info/top_level.txt
ChiMera_ModelBuilder-2.0.15.dist-info/RECORD
